{
    "Ar36": {
        "error": 0.00015403469571728507, 
        "fit": "parabolic", 
        "value": 0.0014063787074453081
    }, 
    "Ar37": {
        "error": 0.014304559818914628, 
        "fit": "linear", 
        "value": 0.16752668390958991
    }, 
    "Ar38": {
        "error": 0.016946224972578961, 
        "fit": "linear", 
        "value": -0.1811757859673655
    }, 
    "Ar39": {
        "error": 0.0095629939272667726, 
        "fit": "parabolic", 
        "value": 0.013471506686071012
    }, 
    "Ar40": {
        "error": 0.022414758939090142, 
        "fit": "parabolic", 
        "value": 0.16824981144193654
    }, 
    "Ar41": {
        "error": 0.0064816751450141449, 
        "fit": "average", 
        "value": 0.22890656604460674
    }
}