{
    "AX": {
        "error": 0.006911443609941945, 
        "fit": "average", 
        "value": 0.007652554011535055
    }, 
    "CDD": {
        "error": 2.54659098573029e-06, 
        "fit": "average", 
        "value": 2.5465909857302903e-06
    }, 
    "H1": {
        "error": 0.015195812965015716, 
        "fit": "average", 
        "value": 0.014554996592535948
    }, 
    "H2": {
        "error": 0.017741905415058153, 
        "fit": "average", 
        "value": -0.11674894147242108
    }, 
    "L1": {
        "error": 0.03011772989113579, 
        "fit": "average", 
        "value": -0.21112011827838917
    }, 
    "L2": {
        "error": 0.019407203346557014, 
        "fit": "average", 
        "value": 0.009900648550440868
    }
}