{
    "AX": {
        "error": 0.005348090112842923, 
        "fit": "average", 
        "value": 0.007969852920480965
    }, 
    "CDD": {
        "error": 2.5142861981152726e-06, 
        "fit": "average", 
        "value": 5.093181971460581e-06
    }, 
    "H1": {
        "error": 0.010512939205220383, 
        "fit": "average", 
        "value": 0.016386159702475804
    }, 
    "H2": {
        "error": 0.011590668236799164, 
        "fit": "average", 
        "value": -0.12099316845609186
    }, 
    "L1": {
        "error": 0.0178514484646937, 
        "fit": "average", 
        "value": -0.19462294502882288
    }, 
    "L2": {
        "error": 0.01122567235673017, 
        "fit": "average", 
        "value": -0.00906759778772539
    }
}