{
    "Ar36": {
        "error": 0.00029592883049513581, 
        "fit": "linear", 
        "value": 0.011621267681577584
    }, 
    "Ar37": {
        "error": 0.028526315202078302, 
        "fit": "linear", 
        "value": 1.9332084658153978
    }, 
    "Ar38": {
        "error": 0.040208723029404432, 
        "fit": "linear", 
        "value": 9.8075427504959443
    }, 
    "Ar39": {
        "error": 0.056587033027031927, 
        "fit": "linear", 
        "value": 800.00048934823769
    }, 
    "Ar40": {
        "error": 0.078412835453913976, 
        "fit": "linear", 
        "value": 1354.4692118105365
    }, 
    "Ar41": {
        "error": 0.015547872835650678, 
        "fit": "average", 
        "value": 0.060476537596744796
    }
}