{
    "Ar36": {
        "error": 0.00033119543390091661, 
        "fit": "linear", 
        "value": 0.017866362994781185
    }, 
    "Ar37": {
        "error": 0.025643903214026972, 
        "fit": "linear", 
        "value": 3.2764985447325299
    }, 
    "Ar38": {
        "error": 0.047181152104616299, 
        "fit": "linear", 
        "value": 14.541870598027515
    }, 
    "Ar39": {
        "error": 0.063353262620676046, 
        "fit": "linear", 
        "value": 1180.1189348747116
    }, 
    "Ar40": {
        "error": 0.10587464991849166, 
        "fit": "linear", 
        "value": 2014.2850427093763
    }, 
    "Ar41": {
        "error": 0.010340937851806587, 
        "fit": "average", 
        "value": 0.2123014011606574
    }
}