{
    "AX": {
        "error": 0.09051135880875935, 
        "fit": "average", 
        "value": 0.10982851143408981
    }, 
    "CDD": {
        "error": 1.2981999229573553e-05, 
        "fit": "average", 
        "value": 0.00012902727661033472
    }, 
    "H1": {
        "error": 0.012279606440709119, 
        "fit": "average", 
        "value": 0.05950792617061072
    }, 
    "H2": {
        "error": 0.015437793885459558, 
        "fit": "average", 
        "value": -0.04773216173311488
    }, 
    "L1": {
        "error": 0.014130431555774205, 
        "fit": "average", 
        "value": -0.15644261025590822
    }, 
    "L2": {
        "error": 0.01286463664772361, 
        "fit": "average", 
        "value": 0.004500789508973766
    }
}