{
    "AX": {
        "error": 0.008587343073868506, 
        "fit": "average", 
        "value": 0.03217260811579384
    }, 
    "CDD": {
        "error": 2.1535730483521517e-05, 
        "fit": "average", 
        "value": 0.0002665431898397704
    }, 
    "H1": {
        "error": 0.014149053195072729, 
        "fit": "average", 
        "value": 0.029363310487113065
    }, 
    "H2": {
        "error": 0.013095868607062857, 
        "fit": "average", 
        "value": 0.270570704796248
    }, 
    "L1": {
        "error": 0.024868358259415975, 
        "fit": "average", 
        "value": -0.0264427921269089
    }, 
    "L2": {
        "error": 0.014281594211415831, 
        "fit": "average", 
        "value": -0.03466995475787876
    }
}