{
    "AX": {
        "error": 0.005889174193436815, 
        "fit": "average", 
        "value": 0.026852076798806794
    }, 
    "CDD": {
        "error": 1.1124012134077662e-05, 
        "fit": "average", 
        "value": 7.97931842195491e-05
    }, 
    "H1": {
        "error": 0.015160457486299222, 
        "fit": "average", 
        "value": 0.011031682119290861
    }, 
    "H2": {
        "error": 0.015156435431157467, 
        "fit": "average", 
        "value": -0.05948234478322168
    }, 
    "L1": {
        "error": 0.03115561092719707, 
        "fit": "average", 
        "value": 0.02215290018874738
    }, 
    "L2": {
        "error": 0.014236936770403335, 
        "fit": "average", 
        "value": 0.0007111892859635797
    }
}