{
    "AX": {
        "error": 0.010011463454737584, 
        "fit": "average", 
        "value": 0.0445629429563673
    }, 
    "CDD": {
        "error": 2.220431229075584e-05, 
        "fit": "average", 
        "value": 0.00027842728175326355
    }, 
    "H1": {
        "error": 0.013375957735880295, 
        "fit": "average", 
        "value": 0.018081644222709452
    }, 
    "H2": {
        "error": 0.013721085516497448, 
        "fit": "average", 
        "value": 0.2514527428170873
    }, 
    "L1": {
        "error": 0.028775834453839556, 
        "fit": "average", 
        "value": -0.04389198425148303
    }, 
    "L2": {
        "error": 0.013775897845502288, 
        "fit": "average", 
        "value": -0.03693332420920746
    }
}