{
    "Ar36": {
        "error": 0.0076044806269688694, 
        "fit": "parabolic", 
        "value": 10.750208631089041
    }, 
    "Ar37": {
        "error": 0.014869513767131304, 
        "fit": "linear", 
        "value": 0.041352192510039493
    }, 
    "Ar38": {
        "error": 0.024889309873853301, 
        "fit": "linear", 
        "value": 1.8333753361329879
    }, 
    "Ar39": {
        "error": 0.011545202331035294, 
        "fit": "parabolic", 
        "value": -0.18279955192916431
    }, 
    "Ar40": {
        "error": 0.13102599971443157, 
        "fit": "parabolic", 
        "value": 3321.084172553069
    }, 
    "Ar41": {
        "error": 0.0069789820054224228, 
        "fit": "average", 
        "value": 0.32333043675404044
    }
}