{
    "Ar36": {
        "error": 0.0066534321115031764, 
        "fit": "parabolic", 
        "value": 10.3447870321517
    }, 
    "Ar37": {
        "error": 0.013308996904850191, 
        "fit": "linear", 
        "value": 0.1504381990916237
    }, 
    "Ar38": {
        "error": 0.017616090693323181, 
        "fit": "linear", 
        "value": 1.7910396851175605
    }, 
    "Ar39": {
        "error": 0.009921875892475689, 
        "fit": "parabolic", 
        "value": -0.034241515150348054
    }, 
    "Ar40": {
        "error": 0.12665100670807089, 
        "fit": "parabolic", 
        "value": 3217.3553200047691
    }, 
    "Ar41": {
        "error": 0.0059191579564928107, 
        "fit": "average", 
        "value": 0.3152942168805748
    }
}