{
    "Ar36": {
        "error": 0.00022458921363179737, 
        "fit": "parabolic", 
        "value": 0.0054520100728236024
    }, 
    "Ar37": {
        "error": 0.013800487791014783, 
        "fit": "linear", 
        "value": 0.072596341354297877
    }, 
    "Ar38": {
        "error": 0.032436397838349493, 
        "fit": "linear", 
        "value": 0.082682233163575009
    }, 
    "Ar39": {
        "error": 0.011220011261898897, 
        "fit": "parabolic", 
        "value": 0.02472723863655207
    }, 
    "Ar40": {
        "error": 0.022751216621216392, 
        "fit": "parabolic", 
        "value": 1.2987884776951497
    }, 
    "Ar41": {
        "error": 0.006692306989618116, 
        "fit": "average", 
        "value": -0.020709889606368961
    }
}