{
    "Ar36": {
        "error": 0.00018369018338061378, 
        "fit": "parabolic", 
        "value": 0.0039604237676110869
    }, 
    "Ar37": {
        "error": 0.013456381642892175, 
        "fit": "linear", 
        "value": 0.14791593630016303
    }, 
    "Ar38": {
        "error": 0.014534291864037046, 
        "fit": "linear", 
        "value": -0.14929303103425501
    }, 
    "Ar39": {
        "error": 0.0099227038245160055, 
        "fit": "parabolic", 
        "value": -0.007871854163639988
    }, 
    "Ar40": {
        "error": 0.021314898137713492, 
        "fit": "parabolic", 
        "value": 0.98895080329598317
    }, 
    "Ar41": {
        "error": 0.0062480522816883814, 
        "fit": "average", 
        "value": -0.038170337885894697
    }
}